examples/demo.py
examples/docs_use_gt.py
examples/test_db.py
examples/test_detect_folder.py
examples/test_draco.py
examples/test_ground_truth.py
examples/test_ground_truth_laptop.py
fmdt/__init__.py
fmdt/api.py
fmdt/args.py
fmdt/config.py
fmdt/core.py
fmdt/db.py
fmdt/download.py
fmdt/exceptions.py
fmdt/res.py
fmdt/stats.py
fmdt/tests.py
fmdt/truth.py
fmdt/utils.py
scripts/explore_config.py
scripts/ground_truth.py
scripts/is_human_detected.py
scripts/light_min_max.py
scripts/load_meteors.py
scripts/movement_stats.py
scripts/new_testing.py
scripts/run_args_results.py
scripts/split_window.py
scripts/windows_test.py
fmdt_python-0.0.45.dist-info/LICENSE
fmdt_python-0.0.45.dist-info/METADATA
fmdt_python-0.0.45.dist-info/WHEEL
fmdt_python-0.0.45.dist-info/top_level.txt
fmdt_python-0.0.45.dist-info/RECORD
