Metadata-Version: 2.1
Name: fmdt-python
Version: 0.0.45
Summary: utlity functions for fast meteor detection toolbox
Author-email: Evan Voyles <ejovo13@yahoo.com>
Project-URL: fmdt, https://github.com/alsoc/fmdt
Project-URL: Homepage, https://github.com/ejovo13/fmdt_scripts
Classifier: Programming Language :: Python :: 3
Classifier: License :: OSI Approved :: MIT License
Classifier: Operating System :: OS Independent
Requires-Python: >=3.10
License-File: LICENSE
Requires-Dist: numpy
Requires-Dist: ffmpeg-python
Requires-Dist: requests
Requires-Dist: termcolor
Requires-Dist: matplotlib
Requires-Dist: pandas
Requires-Dist: jsonpickle
Requires-Dist: appdirs
Requires-Dist: Deprecated
